aiot.py
aiot-0.0.6.dist-info/LICENSE.txt
aiot-0.0.6.dist-info/METADATA
aiot-0.0.6.dist-info/WHEEL
aiot-0.0.6.dist-info/top_level.txt
aiot-0.0.6.dist-info/RECORD
