Metadata-Version: 2.1
Name: aiot
Version: 0.0.6
Summary: aiot sdk in python
Home-page: https://github.com/mobifone-aiot/aiot-python
Author: Đào Ngọc Thành
Author-email: thanh.daongoc10@mobifone.vn
License: UNKNOWN
Platform: UNKNOWN
Classifier: Programming Language :: Python :: 3
Classifier: License :: OSI Approved :: BSD License
Classifier: Operating System :: OS Independent
Provides-Extra: dev
Requires-Dist: pytest (>=3.7) ; extra == 'dev'
